odoo/addons/base_business_document_import/README.rst
odoo/addons/base_business_document_import/__init__.py
odoo/addons/base_business_document_import/__manifest__.py
odoo/addons/base_business_document_import/i18n/base_business_document_import.pot
odoo/addons/base_business_document_import/i18n/cs_CZ.po
odoo/addons/base_business_document_import/i18n/es.po
odoo/addons/base_business_document_import/i18n/fr.po
odoo/addons/base_business_document_import/i18n/fr_FR.po
odoo/addons/base_business_document_import/i18n/it.po
odoo/addons/base_business_document_import/i18n/nl.po
odoo/addons/base_business_document_import/models/__init__.py
odoo/addons/base_business_document_import/models/business_document_import.py
odoo/addons/base_business_document_import/readme/CONTRIBUTORS.md
odoo/addons/base_business_document_import/readme/DESCRIPTION.md
odoo/addons/base_business_document_import/static/description/icon.png
odoo/addons/base_business_document_import/static/description/index.html
odoo/addons/base_business_document_import/tests/__init__.py
odoo/addons/base_business_document_import/tests/test_business_document_import.py
odoo_addon_base_business_document_import-18.0.1.0.1.dist-info/METADATA
odoo_addon_base_business_document_import-18.0.1.0.1.dist-info/WHEEL
odoo_addon_base_business_document_import-18.0.1.0.1.dist-info/top_level.txt
odoo_addon_base_business_document_import-18.0.1.0.1.dist-info/RECORD
