Metadata-Version: 2.1
Name: odoo-addon-base_business_document_import
Version: 18.0.1.0.1
Requires-Python: >=3.10
Requires-Dist: odoo-addon-account_tax_unece==18.0.*
Requires-Dist: odoo-addon-uom_unece==18.0.*
Requires-Dist: odoo==18.0.*
Summary: Provides technical tools to import sale orders or supplier invoices
Home-page: https://github.com/OCA/edi
License: AGPL-3
Author: Akretion, Nicolas JEUDY, Odoo Community Association (OCA)
Author-email: support@odoo-community.org
Classifier: Programming Language :: Python
Classifier: Framework :: Odoo
Classifier: Framework :: Odoo :: 18.0
Classifier: License :: OSI Approved :: GNU Affero General Public License v3
